{
  "runId": "25337175414",
  "actionsRunId": "25337175414",
  "workflowRunUrl": "https://github.com/algorynt-inc/xitester-test/actions/runs/25337175414",
  "commit": "beec7df89d8bc91097f13d7e6decd1c2bf04fbf9",
  "branch": "main",
  "environment": "dev",
  "suite": "orgs",
  "startedAt": "2026-05-04T18:52:17.001Z",
  "finishedAt": "2026-05-04T18:53:33.264Z",
  "durationMs": 76263,
  "stats": {
    "total": 8,
    "passed": 2,
    "failed": 4,
    "skipped": 2,
    "flaky": 0
  },
  "tests": [
    {
      "id": "authenticate once per ru",
      "title": "authenticate once per run",
      "file": "playwright/tests/auth.setup.ts",
      "project": "setup",
      "category": "auth.setup.ts",
      "status": "passed",
      "durationMs": 4458,
      "retries": 0,
      "error": null,
      "attachments": [
        {
          "name": "video",
          "contentType": "video/webm",
          "url": "25337175414/authenticate_once_per_ru-0-video.webm"
        },
        {
          "name": "trace",
          "contentType": "application/zip",
          "url": "25337175414/authenticate_once_per_ru-1-trace.zip"
        }
      ]
    },
    {
      "id": "TC-ORG-001",
      "title": "TC-ORG-001 — View organization list",
      "file": "playwright/tests/orgs.spec.ts",
      "project": "chromium",
      "category": "A. Browse & Search",
      "status": "failed",
      "durationMs": 16263,
      "retries": 1,
      "error": {
        "message": "Error: at least one org card should be visible\n\nexpect(locator).toBeVisible() failed\n\nLocator: locator('main button').filter({ hasNotText: 'New organization' }).first()\nExpected: visible\nTimeout: 10000ms\nError: element(s) not found\n\nCall log:\n  - at least one org card should be visible with timeout 10000ms\n  - waiting for locator('main button').filter({ hasNotText: 'New organization' }).first()\n",
        "snippet": "  71 |             orgButtons.first(),\n  72 |             'at least one org card should be visible',\n> 73 |         ).toBeVisible({ timeout: 10_000 })\n     |           ^\n  74 |     })\n  75 |\n  76 |     test('TC-ORG-002 — Search filters the org list', async ({ page }) => {"
      },
      "attachments": [
        {
          "name": "screenshot",
          "contentType": "image/png",
          "url": "25337175414/TC-ORG-001-0-screenshot.png"
        },
        {
          "name": "video",
          "contentType": "video/webm",
          "url": "25337175414/TC-ORG-001-1-video.webm"
        },
        {
          "name": "error-context",
          "contentType": "text/markdown",
          "url": "25337175414/TC-ORG-001-2-error-context.md"
        },
        {
          "name": "trace",
          "contentType": "application/zip",
          "url": "25337175414/TC-ORG-001-3-trace.zip"
        }
      ]
    },
    {
      "id": "TC-ORG-002",
      "title": "TC-ORG-002 — Search filters the org list",
      "file": "playwright/tests/orgs.spec.ts",
      "project": "chromium",
      "category": "A. Browse & Search",
      "status": "failed",
      "durationMs": 5322,
      "retries": 1,
      "error": {
        "message": "Error: expected at least one org for search test\n\nexpect(received).toBeGreaterThan(expected)\n\nExpected: > 0\nReceived:   0",
        "snippet": "  83 |         const orgButtons = page.locator('main button').filter({ hasNotText: 'New organization' })\n  84 |         const initialCount = await orgButtons.count()\n> 85 |         expect(initialCount, 'expected at least one org for search test').toBeGreaterThan(0)\n     |                                                                           ^\n  86 |\n  87 |         const noMatch = `xt-nomatch-${ts()}`\n  88 |         await search.fill(noMatch)"
      },
      "attachments": [
        {
          "name": "screenshot",
          "contentType": "image/png",
          "url": "25337175414/TC-ORG-002-0-screenshot.png"
        },
        {
          "name": "video",
          "contentType": "video/webm",
          "url": "25337175414/TC-ORG-002-1-video.webm"
        },
        {
          "name": "error-context",
          "contentType": "text/markdown",
          "url": "25337175414/TC-ORG-002-2-error-context.md"
        },
        {
          "name": "trace",
          "contentType": "application/zip",
          "url": "25337175414/TC-ORG-002-3-trace.zip"
        }
      ]
    },
    {
      "id": "TC-ORG-003",
      "title": "TC-ORG-003 — View organization settings",
      "file": "playwright/tests/orgs.spec.ts",
      "project": "chromium",
      "category": "B. View",
      "status": "failed",
      "durationMs": 13289,
      "retries": 1,
      "error": {
        "message": "TimeoutError: locator.click: Timeout 10000ms exceeded.\nCall log:\n  - waiting for locator('main button').filter({ hasNotText: 'New organization' }).first()\n",
        "snippet": "  104 |         await page.goto('/organizations')\n  105 |         const orgButtons = page.locator('main button').filter({ hasNotText: 'New organization' })\n> 106 |         await orgButtons.first().click()\n      |                                  ^\n  107 |\n  108 |         await gotoOrgSettings(page, 'general')\n  109 |"
      },
      "attachments": [
        {
          "name": "screenshot",
          "contentType": "image/png",
          "url": "25337175414/TC-ORG-003-0-screenshot.png"
        },
        {
          "name": "video",
          "contentType": "video/webm",
          "url": "25337175414/TC-ORG-003-1-video.webm"
        },
        {
          "name": "error-context",
          "contentType": "text/markdown",
          "url": "25337175414/TC-ORG-003-2-error-context.md"
        },
        {
          "name": "trace",
          "contentType": "application/zip",
          "url": "25337175414/TC-ORG-003-3-trace.zip"
        }
      ]
    },
    {
      "id": "TC-ORG-004",
      "title": "TC-ORG-004 — Create a new organization",
      "file": "playwright/tests/orgs.spec.ts",
      "project": "chromium",
      "category": "C. Create",
      "status": "skipped",
      "durationMs": 5393,
      "retries": 0,
      "error": null,
      "attachments": [
        {
          "name": "video",
          "contentType": "video/webm",
          "url": "25337175414/TC-ORG-004-0-video.webm"
        },
        {
          "name": "trace",
          "contentType": "application/zip",
          "url": "25337175414/TC-ORG-004-1-trace.zip"
        }
      ]
    },
    {
      "id": "TC-ORG-007",
      "title": "TC-ORG-007 — Create rejects duplicate name",
      "file": "playwright/tests/orgs.spec.ts",
      "project": "chromium",
      "category": "C. Create",
      "status": "skipped",
      "durationMs": 6420,
      "retries": 0,
      "error": null,
      "attachments": [
        {
          "name": "video",
          "contentType": "video/webm",
          "url": "25337175414/TC-ORG-007-0-video.webm"
        },
        {
          "name": "trace",
          "contentType": "application/zip",
          "url": "25337175414/TC-ORG-007-1-trace.zip"
        }
      ]
    },
    {
      "id": "TC-ORG-005",
      "title": "TC-ORG-005 — Update organization name",
      "file": "playwright/tests/orgs.spec.ts",
      "project": "chromium",
      "category": "D. Update",
      "status": "passed",
      "durationMs": 8639,
      "retries": 0,
      "error": null,
      "attachments": [
        {
          "name": "video",
          "contentType": "video/webm",
          "url": "25337175414/TC-ORG-005-0-video.webm"
        },
        {
          "name": "trace",
          "contentType": "application/zip",
          "url": "25337175414/TC-ORG-005-1-trace.zip"
        }
      ]
    },
    {
      "id": "TC-ORG-006",
      "title": "TC-ORG-006 — Delete an organization via danger zone",
      "file": "playwright/tests/orgs.spec.ts",
      "project": "chromium",
      "category": "E. Delete",
      "status": "failed",
      "durationMs": 11439,
      "retries": 1,
      "error": {
        "message": "Error: expect(locator).toBeVisible() failed\n\nLocator: locator('div[role=\"dialog\"] input').first()\nExpected: visible\nTimeout: 5000ms\nError: element(s) not found\n\nCall log:\n  - Expect \"toBeVisible\" with timeout 5000ms\n  - waiting for locator('div[role=\"dialog\"] input').first()\n",
        "snippet": "  316 |\n  317 |         const confirmInput = page.locator('div[role=\"dialog\"] input').first()\n> 318 |         await expect(confirmInput).toBeVisible({ timeout: 5_000 })\n      |                                    ^\n  319 |         await confirmInput.fill(temp.name)\n  320 |\n  321 |         const confirmBtn = page.locator('div[role=\"dialog\"] button', { hasText: /^Delete Organization/ }).first()"
      },
      "attachments": [
        {
          "name": "screenshot",
          "contentType": "image/png",
          "url": "25337175414/TC-ORG-006-0-screenshot.png"
        },
        {
          "name": "video",
          "contentType": "video/webm",
          "url": "25337175414/TC-ORG-006-1-video.webm"
        },
        {
          "name": "error-context",
          "contentType": "text/markdown",
          "url": "25337175414/TC-ORG-006-2-error-context.md"
        },
        {
          "name": "trace",
          "contentType": "application/zip",
          "url": "25337175414/TC-ORG-006-3-trace.zip"
        }
      ]
    }
  ]
}